vuln_demo_math_ops/__init__.py
vuln_demo_math_ops/__version__.py
vuln_demo_math_ops/addition_module.py
vuln_demo_math_ops/division_module.py
vuln_demo_math_ops/multiplication_module.py
vuln_demo_math_ops/subtraction_module.py
vuln_demo_math_ops-1.0.dist-info/LICENSE
vuln_demo_math_ops-1.0.dist-info/METADATA
vuln_demo_math_ops-1.0.dist-info/WHEEL
vuln_demo_math_ops-1.0.dist-info/top_level.txt
vuln_demo_math_ops-1.0.dist-info/RECORD
