Metadata-Version: 2.2
Name: vuln_demo_math_ops
Version: 1.0
Summary: An intentionally vulnerable Python package for testing vulnerability scanners..
Author: Raghu
Author-email: raghu@abc.com
Classifier: Programming Language :: Python :: 3
Classifier: License :: OSI Approved :: MIT License
Classifier: Operating System :: OS Independent
Requires-Python: >=3.8
License-File: LICENSE
Requires-Dist: Django==4.2.18
Requires-Dist: agpt==0.2.2
Requires-Dist: waitress==2.0.0
Requires-Dist: gradio==5.10.0
Requires-Dist: flask==1.0.2
Dynamic: author
Dynamic: author-email
Dynamic: classifier
Dynamic: requires-dist
Dynamic: requires-python
Dynamic: summary
